muoblpsolvers/__init__.py
muoblpsolvers/base_solvers/ElectionSolver.py
muoblpsolvers/base_solvers/__init__.py
muoblpsolvers/common.py
muoblpsolvers/greedy/GreedySolver.py
muoblpsolvers/greedy/__init__.py
muoblpsolvers/mes_add1/MethodOfEqualSharesAdd1Solver.py
muoblpsolvers/mes_add1/__init__.py
muoblpsolvers/mes_constrains/MethodOfEqualSharesConstrainsSolver.py
muoblpsolvers/mes_constrains/__init__.py
muoblpsolvers/mes_constrains/utils.py
muoblpsolvers/mes_exponential/MethodOfEqualSharesExponentialSolver.py
muoblpsolvers/mes_exponential/__init__.py
muoblpsolvers/mes_exponential/mes_exponential.py
muoblpsolvers/mes_utils/MethodOfEqualSharesUtilitySolver.py
muoblpsolvers/mes_utils/__init__.py
muoblpsolvers/phragmen/PhragmenSolver.py
muoblpsolvers/phragmen/__init__.py
muoblpsolvers/summed/SummedObjectivesLpSolver.py
muoblpsolvers/summed/__init__.py
muoblpsolvers/types.py
muoblpsolvers-0.0.13.dist-info/METADATA
muoblpsolvers-0.0.13.dist-info/WHEEL
muoblpsolvers-0.0.13.dist-info/RECORD
