Metadata-Version: 2.4
Name: muoblpsolvers
Version: 0.0.13
Summary: Solvers for multi objective linear programming
License-Expression: MIT
Author: Piotr Skowron
Author-email: p.skowron@mimuw.edu.pl
Requires-Python: >=3.11
Classifier: Programming Language :: Python :: 3
Classifier: Programming Language :: Python :: 3.11
Classifier: Programming Language :: Python :: 3.12
Classifier: Programming Language :: Python :: 3.13
Classifier: Programming Language :: Python :: 3.14
Requires-Dist: muoblp (==1.0.3)
Requires-Dist: muoblpbindings (==0.0.16)
Requires-Dist: pulp (==2.9.0)
Requires-Dist: pytest (==8.4.1)
Project-URL: Documentation, https://jasieksz.github.io/multiobjective-lp
Project-URL: Repository, https://github.com/jasieksz/multiobjective-lp
